{
  "Textures": {
    "PM_Diffuse": "/Game/Art/Enviroment/Natrue/T_DJ09_Acc_unit_v23_D_VD.T_DJ09_Acc_unit_v23_D_VD",
    "Diffuse": "/Game/Art/Enviroment/Natrue/T_DJ09_Acc_unit_v23_D_VD.T_DJ09_Acc_unit_v23_D_VD",
    "PM_Normals": "/Game/Art/Enviroment/Natrue/T_DJ09_Acc_unit_v23_N_VD.T_DJ09_Acc_unit_v23_N_VD",
    "Normal": "/Game/Art/Enviroment/Natrue/T_DJ09_Acc_unit_v23_N_VD.T_DJ09_Acc_unit_v23_N_VD"
  },
  "Parameters": {
    "BlendMode": 0,
    "ShadingModel": 0,
    "Colors": {},
    "Scalars": {
      "RefractionDepthBias": 0.0
    },
    "Switches": {},
    "Properties": {
      "BasePropertyOverrides": {
        "OpacityMaskClipValue": 0.3333
      },
      "bIncludedInBaseGame": true
    },
    "HasTopDiffuse": true,
    "HasTopNormals": true,
    "HasTopSpecularMasks": false,
    "HasTopEmissive": false,
    "IsTranslucent": false,
    "IsNull": false
  }
}